Examples/DMD/example_DMD_channel.py
Examples/DMD/example_DMD_cylinder.py
Examples/DMD/example_DMD_jet.py
Examples/GPOD/example_GPOD.py
Examples/GPOD/example_GPOD_vector.py
Examples/GPR/example_GPR.py
Examples/MANIFOLD/example_isomap_cylinder.py
Examples/MANIFOLD/example_mds_cylinder.py
Examples/NN/example_AE_cylinder.py
Examples/NN/example_KAN_DLR_airfoil.py
Examples/NN/example_KAN_xfoil_dataset.py
Examples/NN/example_MLP_DLR_airfoil.py
Examples/NN/example_MLP_xfoil_dataset.py
Examples/NN/example_PINN_Burgers.py
Examples/NN/example_VAE_T280.py
Examples/NN/example_VAE_channel.py
Examples/NN/example_VAE_cylinder.py
Examples/NN/example_VAE_cylinder_finetune.py
Examples/NN/example_VAE_cylinder_ft.py
Examples/NN/example_optuna_KAN_DLR_airfoil.py
Examples/NN/example_optuna_MLP_DLR_airfoil.py
Examples/NN/SHRED/example_01_SVD_and_sensors_cylinder.py
Examples/NN/SHRED/example_02_fit_shred_cylinder.py
Examples/NN/SHRED/example_03_inference_shred_cylinder.py
Examples/NN/SHRED/example_04_reconstruct_cylinder.py
Examples/POD/example_POD_T280.py
Examples/POD/example_POD_channel.py
Examples/POD/example_POD_cylinder.py
Examples/POD/example_POD_cylinder_energy.py
Examples/POD/example_POD_cylinder_randomized.py
Examples/POD/example_POD_jet.py
Examples/POD/example_POD_matrix.py
Examples/POD/example_POD_tgv.py
Examples/RL/eval_agent_mpi.py
Examples/RL/fine_tune_agent.py
Examples/RL/optuna_optimization.py
Examples/RL/train_agent_airfoil.py
Examples/RL/train_agent_wing.py
Examples/SPOD/example_SPOD_T280.py
Examples/SPOD/example_SPOD_channel.py
Examples/SPOD/example_SPOD_cylinder.py
Examples/SPOD/example_SPOD_jet.py
Examples/scalability/example_SVD_GPU_strong.py
Examples/scalability/example_SVD_GPU_weakM.py
Testsuite/Converters/tsuite_dset_T280.py
Testsuite/Converters/tsuite_dset_channel.py
Testsuite/Converters/tsuite_dset_cylinder.py
Testsuite/Converters/tsuite_dset_jet.py
Testsuite/Converters/tsuite_dset_synthetic.py
Testsuite/runs/tsuite_AE2D.py
Testsuite/runs/tsuite_DMD.py
pyloworder-3.2.5.dist-info/licenses/LICENSE
pyloworder-3.2.5.dist-info/METADATA
pyloworder-3.2.5.dist-info/WHEEL
pyloworder-3.2.5.dist-info/top_level.txt
pyloworder-3.2.5.dist-info/RECORD
