Metadata-Version: 2.4
Name: pyLowOrder
Version: 3.2.5
Summary: High-performance low-order modeling with Python
Home-page: https://github.com/ArnauMiro/pyLowOrder
Author: Benet Eiximeno, Beka Begiashvili, Arnau Miro, Eusebio Valero, Oriol Lehmkuhl
Author-email: Benet Eiximeno <benet.eiximeno@bsc.es>, Beka Begiashvili <beka.begiashvili@alumnos.upm.es>, Arnau Miro <arnau.mirojane@bsc.es>, Eusebio Valero <eusebio.valero@upm.es>, Oriol Lehmkuhl <oriol.lehmkuhl@bsc.es>
Maintainer: Benet Eiximeno, Arnau Miro
Maintainer-email: Benet Eiximeno <benet.eiximeno@bsc.es>, Arnau Miro <arnau.mirojane@bsc.es>
License-Expression: MIT
Project-URL: Homepage, https://ArnauMiro@github.com/ArnauMiro/pyLowOrder
Project-URL: Bug Reports, https://ArnauMiro@github.com/ArnauMiro/pyLowOrder/issues
Project-URL: Source, https://ArnauMiro@github.com/ArnauMiro/pyLowOrder
Keywords: low-order,modeling,POD,DMD
Classifier: Development Status :: 5 - Production/Stable
Classifier: Intended Audience :: Science/Research
Classifier: Topic :: Scientific/Engineering
Classifier: Programming Language :: Python :: 3
Classifier: Programming Language :: Python :: 3.9
Classifier: Programming Language :: Python :: 3.10
Classifier: Programming Language :: Python :: 3.11
Classifier: Programming Language :: Python :: 3.12
Classifier: Programming Language :: Python :: 3 :: Only
Requires-Python: >=3.9
License-File: LICENSE
Requires-Dist: numpy
Requires-Dist: cython>=3.0.0
Requires-Dist: mpi4py>=4.0.0
Requires-Dist: matplotlib
Requires-Dist: h5py>=3.0.0
Requires-Dist: nfft
Provides-Extra: cuda
Requires-Dist: cupy; extra == "cuda"
Provides-Extra: cuda12x
Requires-Dist: cupy-cuda12x; extra == "cuda12x"
Provides-Extra: cuda11x
Requires-Dist: cupy-cuda11x; extra == "cuda11x"
Provides-Extra: rocm-4-0
Requires-Dist: cupy-rocm-4-0; extra == "rocm-4-0"
Provides-Extra: nn
Requires-Dist: torch>=2.3.0; extra == "nn"
Requires-Dist: torchvision; extra == "nn"
Requires-Dist: torchsummary; extra == "nn"
Requires-Dist: tensorflow; extra == "nn"
Requires-Dist: optuna; extra == "nn"
Provides-Extra: gpr
Requires-Dist: GPy; extra == "gpr"
Requires-Dist: emukit; extra == "gpr"
Requires-Dist: h5py<=3.10.0; extra == "gpr"
Provides-Extra: optionals
Requires-Dist: pyvista; extra == "optionals"
Requires-Dist: scikit-learn; extra == "optionals"
Requires-Dist: nvtx; extra == "optionals"
Provides-Extra: rl
Requires-Dist: AeroSandbox; extra == "rl"
Requires-Dist: gymnasium>=1.1.1; extra == "rl"
Requires-Dist: stable_baselines3; extra == "rl"
Requires-Dist: neuralFoil-torch; extra == "rl"
Dynamic: author
Dynamic: home-page
Dynamic: license-file
Dynamic: maintainer
